{
  "inventario": [
    {
      "id": "c182",
      "codigo": "102",
      "nombre": "Culantro",
      "cantidad": 50,
      "precio": 300,
      "url": ""
    },
    {
      "id": "ea44",
      "nombre": "papaya",
      "completed": false
    },
    {
      "id": "2bbe",
      "nombre": "Yuca",
      "completed": false
    },
    {
      "id": "34ae",
      "nombre": "Melon",
      "completed": false
    },
    {
      "id": "97de",
      "nombre": "Zanahoria",
      "completed": false
    },
    {
      "id": "20d2",
      "codigo": "101",
      "nombre": "Lechuga americana",
      "cantidad": 30,
      "precio": 350,
      "url": ""
    },
    {
      "id": "6ee3",
      "codigo": "103",
      "nombre": "Rabano",
      "cantidad": 10,
      "precio": 350,
      "url": " ../assets/img/aguacate.jpg"
    },
    {
      "id": "fa81",
      "codigo": "104",
      "nombre": "Aguacate",
      "cantidad": 100,
      "precio": 500,
      "url": " ../assets/img/aguacate.jpg"
    }
  ],
  "users": [
    {
      "id": "ea3e",
      "nombre": "sdfhsdfJuan",
      "apellido": "Quesada Ramírez",
      "correo": "juan@gmail.com",
      "contrasena": "asf1234",
      "promociones": true
    },
    {
      "id": "36f7",
      "nombre": "Pablo",
      "apellido": "Jimenez",
      "correo": "pjimenez@gmail.com",
      "contrasena": "45678",
      "promociones": false
    }
  ]
}